{
  "project_info": {
    "project_id": "my-project-for-hiapp",
    "project_number": "39764648669",
    "name": "My Project for HiApp"
  },
  "client": [
    {
      "client_info": {
        "mobilesdk_app_id": "1:39764648669:android:27d689d63f1b7a06",
        "client_id": "android:com.google.samples.quickstart.signin",
        "client_type": 1,
        "android_client_info": {
          "package_name": "com.google.samples.quickstart.signin",
          "certificate_hash": []
        }
      },
      "oauth_client": [
        {
          "client_id": "39764648669-7ptphtl62eags8dtis6evc9ucni06t9q.apps.googleusercontent.com",
          "client_type": 3
        }
      ],
      "api_key": [],
      "services": {
        "analytics_service": {
          "status": 1
        },
        "cloud_messaging_service": {
          "status": 1,
          "apns_config": []
        },
        "appinvite_service": {
          "status": 1,
          "other_platform_oauth_client": []
        },
        "google_signin_service": {
          "status": 1
        },
        "ads_service": {
          "status": 2,
          "test_banner_ad_unit_id": "ca-app-pub-3940256099942544/6300978111",
          "test_interstitial_ad_unit_id": "ca-app-pub-3940256099942544/1033173712"
        }
      }
    },
    {
      "client_info": {
        "mobilesdk_app_id": "1:39764648669:android:d5b1d553673bb7d3",
        "client_id": "android:com.asaewing.hiapp_d1v0_4v4",
        "client_type": 1,
        "android_client_info": {
          "package_name": "com.asaewing.hiapp_d1v0_4v4",
          "certificate_hash": []
        }
      },
      "oauth_client": [
        {
          "client_id": "39764648669-7ptphtl62eags8dtis6evc9ucni06t9q.apps.googleusercontent.com",
          "client_type": 3
        }
      ],
      "api_key": [],
      "services": {
        "analytics_service": {
          "status": 1
        },
        "cloud_messaging_service": {
          "status": 1,
          "apns_config": []
        },
        "appinvite_service": {
          "status": 1,
          "other_platform_oauth_client": []
        },
        "google_signin_service": {
          "status": 1
        },
        "ads_service": {
          "status": 2,
          "test_banner_ad_unit_id": "ca-app-pub-3940256099942544/6300978111",
          "test_interstitial_ad_unit_id": "ca-app-pub-3940256099942544/1033173712"
        }
      }
    },
    {
      "client_info": {
        "mobilesdk_app_id": "1:39764648669:android:9304a999e7094d48",
        "client_id": "android:com.asaewing.healthimprover",
        "client_type": 1,
        "android_client_info": {
          "package_name": "com.asaewing.healthimprover",
          "certificate_hash": []
        }
      },
      "oauth_client": [
        {
          "client_id": "39764648669-uliqafoo87tbbnak9ma86prg6vgn76m5.apps.googleusercontent.com",
          "client_type": 1,
          "android_info": {
            "package_name": "com.asaewing.healthimprover",
            "certificate_hash": "5ED0582EE2060783318E9D557661E8230DD0A59C"
          }
        },
        {
          "client_id": "39764648669-7ptphtl62eags8dtis6evc9ucni06t9q.apps.googleusercontent.com",
          "client_type": 3
        }
      ],
      "api_key": [],
      "services": {
        "analytics_service": {
          "status": 1
        },
        "cloud_messaging_service": {
          "status": 2,
          "apns_config": []
        },
        "appinvite_service": {
          "status": 2,
          "other_platform_oauth_client": [
            {
              "client_id": "39764648669-7ptphtl62eags8dtis6evc9ucni06t9q.apps.googleusercontent.com",
              "client_type": 3
            }
          ]
        },
        "google_signin_service": {
          "status": 2
        },
        "ads_service": {
          "status": 2,
          "test_banner_ad_unit_id": "ca-app-pub-3940256099942544/6300978111",
          "test_interstitial_ad_unit_id": "ca-app-pub-3940256099942544/1033173712"
        }
      }
    }
  ],
  "client_info": [],
  "ARTIFACT_VERSION": "1"
}